sphinxcontrib_jsmath-1.0.0-py3.7-nspkg.pth
sphinxcontrib/jsmath/__init__.py
sphinxcontrib/jsmath/version.py
sphinxcontrib_jsmath-1.0.0.dist-info/LICENSE
sphinxcontrib_jsmath-1.0.0.dist-info/METADATA
sphinxcontrib_jsmath-1.0.0.dist-info/WHEEL
sphinxcontrib_jsmath-1.0.0.dist-info/namespace_packages.txt
sphinxcontrib_jsmath-1.0.0.dist-info/top_level.txt
sphinxcontrib_jsmath-1.0.0.dist-info/RECORD
